mlipx/__init__.py
mlipx/__init__.pyi
mlipx/abc.py
mlipx/doc_utils.py
mlipx/models.py
mlipx/project.py
mlipx/utils.py
mlipx/version.py
mlipx/benchmark/__init__.py
mlipx/benchmark/elements.py
mlipx/benchmark/file.py
mlipx/benchmark/main.py
mlipx/cli/__init__.py
mlipx/cli/main.py
mlipx/nodes/__init__.py
mlipx/nodes/adsorption.py
mlipx/nodes/apply_calculator.py
mlipx/nodes/autowte.py
mlipx/nodes/compare_calculator.py
mlipx/nodes/diatomics.py
mlipx/nodes/energy_volume.py
mlipx/nodes/evaluate_calculator.py
mlipx/nodes/filter_dataset.py
mlipx/nodes/formation_energy.py
mlipx/nodes/generic_ase.py
mlipx/nodes/invariances.py
mlipx/nodes/io.py
mlipx/nodes/modifier.py
mlipx/nodes/molecular_dynamics.py
mlipx/nodes/mp_api.py
mlipx/nodes/nebs.py
mlipx/nodes/observer.py
mlipx/nodes/orca.py
mlipx/nodes/phase_diagram.py
mlipx/nodes/pourbaix_diagram.py
mlipx/nodes/rattle.py
mlipx/nodes/smiles.py
mlipx/nodes/structure_optimization.py
mlipx/nodes/updated_frames.py
mlipx/nodes/vibrational_analysis.py
mlipx/recipes/README.md
mlipx/recipes/__init__.py
mlipx/recipes/adsorption.py.jinja2
mlipx/recipes/energy_volume.py.jinja2
mlipx/recipes/homonuclear_diatomics.py.jinja2
mlipx/recipes/invariances.py.jinja2
mlipx/recipes/main.py
mlipx/recipes/md.py.jinja2
mlipx/recipes/metrics.py
mlipx/recipes/models.py.jinja2
mlipx/recipes/neb.py
mlipx/recipes/phase_diagram.py.jinja2
mlipx/recipes/pourbaix_diagram.py.jinja2
mlipx/recipes/relax.py.jinja2
mlipx/recipes/vibrational_analysis.py.jinja2
mlipx/spec/__init__.py
mlipx/spec/compare.py
mlipx/spec/datasets-schema.json
mlipx/spec/datasets.yaml
mlipx/spec/mlips-schema.json
mlipx/spec/mlips.yaml
mlipx/spec/spec.py
mlipx-0.1.5.dist-info/METADATA
mlipx-0.1.5.dist-info/WHEEL
mlipx-0.1.5.dist-info/entry_points.txt
mlipx-0.1.5.dist-info/licenses/LICENSE
mlipx-0.1.5.dist-info/RECORD
