Metadata-Version: 2.4
Name: mlipx
Version: 0.1.5
Summary: Machine-Learned Interatomic Potential eXploration
Author-email: Sandip De <sandip.de@basf.com>, Fabian Zills <fzills@icp.uni-stuttgart.de>, Sheena Agarwal <sheena.a.agarwal@basf.com>
License-Expression: MIT
License-File: LICENSE
Keywords: collaboration,data-version-control,machine-learned interatomic potential,machine-learning,mlff,mlip,reproducibility
Requires-Python: >=3.10
Requires-Dist: ase>=3.24.0
Requires-Dist: dvc-s3>=3.2.0
Requires-Dist: lazy-loader>=0.4
Requires-Dist: mp-api>=0.45.3
Requires-Dist: mpcontribs-client>=5.10.2
Requires-Dist: plotly>=6.0.0
Requires-Dist: pydantic>=2.10.6
Requires-Dist: rdkit2ase>=0.1.4
Requires-Dist: typer>=0.15.1
Requires-Dist: zndraw>=0.5.10
Requires-Dist: znh5md>=0.4.4
Requires-Dist: zntrack>=0.8.5
Provides-Extra: chgnet
Requires-Dist: chgnet>=0.4.0; extra == 'chgnet'
Provides-Extra: fairchem
Requires-Dist: fairchem-core>=2.1.0; extra == 'fairchem'
Provides-Extra: grace
Requires-Dist: tensorpotential>=0.5.1; extra == 'grace'
Provides-Extra: mace
Requires-Dist: mace-torch>=0.3.12; extra == 'mace'
Provides-Extra: matpes
Requires-Dist: matgl>=1.2.7; extra == 'matpes'
Requires-Dist: matpes>=0.0.3; extra == 'matpes'
Provides-Extra: mattersim
Requires-Dist: mattersim>=1.1.2; extra == 'mattersim'
Provides-Extra: orb
Requires-Dist: orb-models>=0.5.0; extra == 'orb'
Provides-Extra: pet-mad
Requires-Dist: pet-mad>=1.2.0; extra == 'pet-mad'
Provides-Extra: sevenn
Requires-Dist: sevenn>=0.11.0; extra == 'sevenn'
